{"symbol": "CGC", "annualReports": [{"fiscalDateEnding": "2021-03-31", "reportedCurrency": "CAD", "operatingCashflow": "-465729000", "paymentsForOperatingActivities": "43235000", "proceedsFromOperatingActivities": "None", "changeInOperatingLiabilities": "-9627000", "changeInOperatingAssets": "-5294000", "depreciationDepletionAndAmortization": "129421000", "capitalExpenditures": "218862000", "changeInReceivables": "11994000", "changeInInventory": "-17211000", "profitLoss": "-1670820000", "cashflowFromInvestment": "-884105000", "cashflowFromFinancing": "1264769000", "proceedsFromRepaymentsOfShortTermDebt": "None", "paymentsForRepurchaseOfCommonStock": "None", "paymentsForRepurchaseOfEquity": "None", "paymentsForRepurchaseOfPreferredStock": "None", "dividendPayout": "None", "dividendPayoutCommonStock": "None", "dividendPayoutPreferredStock": "None", "proceedsFromIssuanceOfCommonStock": "None", "proceedsFromIssuanceOfLongTermDebtAndCapitalSecuritiesNet": "893160000", "proceedsFromIssuanceOfPreferredStock": "None", "proceedsFromRepurchaseOfEquity": "402083000", "proceedsFromSaleOfTreasuryStock": "None", "changeInCashAndCashEquivalents": "-87756000", "changeInExchangeRate": "-2691000", "netIncome": "-1744920000"}, {"fiscalDateEnding": "2020-03-31", "reportedCurrency": "CAD", "operatingCashflow": "-772635000", "paymentsForOperatingActivities": "19878000", "proceedsFromOperatingActivities": "None", "changeInOperatingLiabilities": "-20750000", "changeInOperatingAssets": "183029000", "depreciationDepletionAndAmortization": "126507000", "capitalExpenditures": "851491000", "changeInReceivables": "-20979000", "changeInInventory": "177091000", "profitLoss": "-1387440000", "cashflowFromInvestment": "-347654000", "cashflowFromFinancing": "-57161000", "proceedsFromRepaymentsOfShortTermDebt": "None", "paymentsForRepurchaseOfCommonStock": "None", "paymentsForRepurchaseOfEquity": "None", "paymentsForRepurchaseOfPreferredStock": "None", "dividendPayout": "None", "dividendPayoutCommonStock": "None", "dividendPayoutPreferredStock": "None", "proceedsFromIssuanceOfCommonStock": "None", "proceedsFromIssuanceOfLongTermDebtAndCapitalSecuritiesNet": "14761000", "proceedsFromIssuanceOfPreferredStock": "None", "proceedsFromRepurchaseOfEquity": "41859000", "proceedsFromSaleOfTreasuryStock": "None", "changeInCashAndCashEquivalents": "-1177450000", "changeInExchangeRate": "None", "netIncome": "-1321326000"}, {"fiscalDateEnding": "2019-03-31", "reportedCurrency": "CAD", "operatingCashflow": "-535031000", "paymentsForOperatingActivities": "502000", "proceedsFromOperatingActivities": "None", "changeInOperatingLiabilities": "69540000", "changeInOperatingAssets": "300081000", "depreciationDepletionAndAmortization": "46918000", "capitalExpenditures": "810152000", "changeInReceivables": "67688000", "changeInInventory": "144917000", "profitLoss": "-712025000", "cashflowFromInvestment": "-3227985000", "cashflowFromFinancing": "5851719000", "proceedsFromRepaymentsOfShortTermDebt": "None", "paymentsForRepurchaseOfCommonStock": "None", "paymentsForRepurchaseOfEquity": "None", "paymentsForRepurchaseOfPreferredStock": "None", "dividendPayout": "None", "dividendPayoutCommonStock": "None", "dividendPayoutPreferredStock": "None", "proceedsFromIssuanceOfCommonStock": "5072500000", "proceedsFromIssuanceOfLongTermDebtAndCapitalSecuritiesNet": "600000000", "proceedsFromIssuanceOfPreferredStock": "None", "proceedsFromRepurchaseOfEquity": "66949000", "proceedsFromSaleOfTreasuryStock": "None", "changeInCashAndCashEquivalents": "2158270000", "changeInExchangeRate": "69567000", "netIncome": "-736281000"}, {"fiscalDateEnding": "2018-03-31", "reportedCurrency": "CAD", "operatingCashflow": "-81506000", "paymentsForOperatingActivities": "None", "proceedsFromOperatingActivities": "None", "changeInOperatingLiabilities": "27130000", "changeInOperatingAssets": "53319000", "depreciationDepletionAndAmortization": "20486000", "capitalExpenditures": "200533000", "changeInReceivables": "15738000", "changeInInventory": "21811000", "profitLoss": "-51064000", "cashflowFromInvestment": "-223583000", "cashflowFromFinancing": "525849000", "proceedsFromRepaymentsOfShortTermDebt": "None", "paymentsForRepurchaseOfCommonStock": "None", "paymentsForRepurchaseOfEquity": "None", "paymentsForRepurchaseOfPreferredStock": "None", "dividendPayout": "None", "dividendPayoutCommonStock": "None", "dividendPayoutPreferredStock": "None", "proceedsFromIssuanceOfCommonStock": "470670000", "proceedsFromIssuanceOfLongTermDebtAndCapitalSecuritiesNet": "None", "proceedsFromIssuanceOfPreferredStock": "None", "proceedsFromRepurchaseOfEquity": "11823000", "proceedsFromSaleOfTreasuryStock": "None", "changeInCashAndCashEquivalents": "220760000", "changeInExchangeRate": "None", "netIncome": "-67283000"}], "quarterlyReports": [{"fiscalDateEnding": "2021-09-30", "reportedCurrency": "CAD", "operatingCashflow": "-85965000", "paymentsForOperatingActivities": "60021000", "proceedsFromOperatingActivities": "None", "changeInOperatingLiabilities": "20738000", "changeInOperatingAssets": "-18661000", "depreciationDepletionAndAmortization": "28780000", "capitalExpenditures": "17275000", "changeInReceivables": "-17300000", "changeInInventory": "4020000", "profitLoss": "-16331000", "cashflowFromInvestment": "328262000", "cashflowFromFinancing": "-1713000", "proceedsFromRepaymentsOfShortTermDebt": "None", "paymentsForRepurchaseOfCommonStock": "None", "paymentsForRepurchaseOfEquity": "None", "paymentsForRepurchaseOfPreferredStock": "None", "dividendPayout": "None", "dividendPayoutCommonStock": "None", "dividendPayoutPreferredStock": "None", "proceedsFromIssuanceOfCommonStock": "None", "proceedsFromIssuanceOfLongTermDebtAndCapitalSecuritiesNet": "0", "proceedsFromIssuanceOfPreferredStock": "None", "proceedsFromRepurchaseOfEquity": "1294000", "proceedsFromSaleOfTreasuryStock": "None", "changeInCashAndCashEquivalents": "-192444000", "changeInExchangeRate": "971000", "netIncome": "-11058000"}, {"fiscalDateEnding": "2021-06-30", "reportedCurrency": "CAD", "operatingCashflow": "-165780000", "paymentsForOperatingActivities": "330000", "proceedsFromOperatingActivities": "None", "changeInOperatingLiabilities": "-16960000", "changeInOperatingAssets": "-30478000", "depreciationDepletionAndAmortization": "25132000", "capitalExpenditures": "21112000", "changeInReceivables": "4946000", "changeInInventory": "-44228000", "profitLoss": "389955000", "cashflowFromInvestment": "-374559000", "cashflowFromFinancing": "-44968000", "proceedsFromRepaymentsOfShortTermDebt": "None", "paymentsForRepurchaseOfCommonStock": "None", "paymentsForRepurchaseOfEquity": "None", "paymentsForRepurchaseOfPreferredStock": "None", "dividendPayout": "None", "dividendPayoutCommonStock": "None", "dividendPayoutPreferredStock": "None", "proceedsFromIssuanceOfCommonStock": "None", "proceedsFromIssuanceOfLongTermDebtAndCapitalSecuritiesNet": "0", "proceedsFromIssuanceOfPreferredStock": "None", "proceedsFromRepurchaseOfEquity": "3592000", "proceedsFromSaleOfTreasuryStock": "None", "changeInCashAndCashEquivalents": "-585837000", "changeInExchangeRate": "-530000", "netIncome": "392418000"}, {"fiscalDateEnding": "2021-03-31", "reportedCurrency": "CAD", "operatingCashflow": "-97830000", "paymentsForOperatingActivities": "22859000", "proceedsFromOperatingActivities": "None", "changeInOperatingLiabilities": "-1384000", "changeInOperatingAssets": "-50674000", "depreciationDepletionAndAmortization": "31231000", "capitalExpenditures": "39411000", "changeInReceivables": "-513000", "changeInInventory": "-45731000", "profitLoss": "-616695000", "cashflowFromInvestment": "-555187000", "cashflowFromFinancing": "995629000", "proceedsFromRepaymentsOfShortTermDebt": "None", "paymentsForRepurchaseOfCommonStock": "None", "paymentsForRepurchaseOfEquity": "None", "paymentsForRepurchaseOfPreferredStock": "None", "dividendPayout": "None", "dividendPayoutCommonStock": "None", "dividendPayoutPreferredStock": "None", "proceedsFromIssuanceOfCommonStock": "None", "proceedsFromIssuanceOfLongTermDebtAndCapitalSecuritiesNet": "0", "proceedsFromIssuanceOfPreferredStock": "None", "proceedsFromRepurchaseOfEquity": "119094000", "proceedsFromSaleOfTreasuryStock": "None", "changeInCashAndCashEquivalents": "-616695000", "changeInExchangeRate": "-539000", "netIncome": "-699978000"}, {"fiscalDateEnding": "2020-12-31", "reportedCurrency": "CAD", "operatingCashflow": "-87604000", "paymentsForOperatingActivities": "4789000", "proceedsFromOperatingActivities": "None", "changeInOperatingLiabilities": "3165000", "changeInOperatingAssets": "16774000", "depreciationDepletionAndAmortization": "32385000", "capitalExpenditures": "74126000", "changeInReceivables": "14005000", "changeInInventory": "5020000", "profitLoss": "-829251000", "cashflowFromInvestment": "239212000", "cashflowFromFinancing": "18335000", "proceedsFromRepaymentsOfShortTermDebt": "None", "paymentsForRepurchaseOfCommonStock": "None", "paymentsForRepurchaseOfEquity": "None", "paymentsForRepurchaseOfPreferredStock": "None", "dividendPayout": "None", "dividendPayoutCommonStock": "None", "dividendPayoutPreferredStock": "None", "proceedsFromIssuanceOfCommonStock": "None", "proceedsFromIssuanceOfLongTermDebtAndCapitalSecuritiesNet": "0", "proceedsFromIssuanceOfPreferredStock": "None", "proceedsFromRepurchaseOfEquity": "27243000", "proceedsFromSaleOfTreasuryStock": "None", "changeInCashAndCashEquivalents": "-211802000", "changeInExchangeRate": "None", "netIncome": "-904380000"}, {"fiscalDateEnding": "2020-09-30", "reportedCurrency": "CAD", "operatingCashflow": "-161749000", "paymentsForOperatingActivities": "15179000", "proceedsFromOperatingActivities": "None", "changeInOperatingLiabilities": "-15163000", "changeInOperatingAssets": "19352000", "depreciationDepletionAndAmortization": "31758000", "capitalExpenditures": "38126000", "changeInReceivables": "16079000", "changeInInventory": "12728000", "profitLoss": "-96552000", "cashflowFromInvestment": "-142146000", "cashflowFromFinancing": "3502000", "proceedsFromRepaymentsOfShortTermDebt": "None", "paymentsForRepurchaseOfCommonStock": "None", "paymentsForRepurchaseOfEquity": "None", "paymentsForRepurchaseOfPreferredStock": "None", "dividendPayout": "None", "dividendPayoutCommonStock": "None", "dividendPayoutPreferredStock": "None", "proceedsFromIssuanceOfCommonStock": "None", "proceedsFromIssuanceOfLongTermDebtAndCapitalSecuritiesNet": "-2875000", "proceedsFromIssuanceOfPreferredStock": "None", "proceedsFromRepurchaseOfEquity": "6034000", "proceedsFromSaleOfTreasuryStock": "None", "changeInCashAndCashEquivalents": "-96265000", "changeInExchangeRate": "None", "netIncome": "-32061000"}, {"fiscalDateEnding": "2020-06-30", "reportedCurrency": "CAD", "operatingCashflow": "-118546000", "paymentsForOperatingActivities": "408000", "proceedsFromOperatingActivities": "None", "changeInOperatingLiabilities": "3755000", "changeInOperatingAssets": "9254000", "depreciationDepletionAndAmortization": "34047000", "capitalExpenditures": "67199000", "changeInReceivables": "-17577000", "changeInInventory": "10772000", "profitLoss": "-128322000", "cashflowFromInvestment": "-425984000", "cashflowFromFinancing": "247303000", "proceedsFromRepaymentsOfShortTermDebt": "None", "paymentsForRepurchaseOfCommonStock": "None", "paymentsForRepurchaseOfEquity": "None", "paymentsForRepurchaseOfPreferredStock": "None", "dividendPayout": "None", "dividendPayoutCommonStock": "None", "dividendPayoutPreferredStock": "None", "proceedsFromIssuanceOfCommonStock": "None", "proceedsFromIssuanceOfLongTermDebtAndCapitalSecuritiesNet": "4439000", "proceedsFromIssuanceOfPreferredStock": "None", "proceedsFromRepurchaseOfEquity": "249712000", "proceedsFromSaleOfTreasuryStock": "None", "changeInCashAndCashEquivalents": "-297227000", "changeInExchangeRate": "None", "netIncome": "-108501000"}, {"fiscalDateEnding": "2020-03-31", "reportedCurrency": "CAD", "operatingCashflow": "-210639000", "paymentsForOperatingActivities": "16658000", "proceedsFromOperatingActivities": "None", "changeInOperatingLiabilities": "-9191000", "changeInOperatingAssets": "-49991000", "depreciationDepletionAndAmortization": "50275000", "capitalExpenditures": "180262000", "changeInReceivables": "-7230000", "changeInInventory": "-63464000", "profitLoss": "-1326405000", "cashflowFromInvestment": "-66205000", "cashflowFromFinancing": "14195000", "proceedsFromRepaymentsOfShortTermDebt": "None", "paymentsForRepurchaseOfCommonStock": "None", "paymentsForRepurchaseOfEquity": "None", "paymentsForRepurchaseOfPreferredStock": "None", "dividendPayout": "None", "dividendPayoutCommonStock": "None", "dividendPayoutPreferredStock": "None", "proceedsFromIssuanceOfCommonStock": "None", "proceedsFromIssuanceOfLongTermDebtAndCapitalSecuritiesNet": "4493000", "proceedsFromIssuanceOfPreferredStock": "None", "proceedsFromRepurchaseOfEquity": "2264000", "proceedsFromSaleOfTreasuryStock": "None", "changeInCashAndCashEquivalents": "-1326405000", "changeInExchangeRate": "None", "netIncome": "-1303021000"}, {"fiscalDateEnding": "2019-12-31", "reportedCurrency": "CAD", "operatingCashflow": "-189911000", "paymentsForOperatingActivities": "1915000", "proceedsFromOperatingActivities": "None", "changeInOperatingLiabilities": "-22143000", "changeInOperatingAssets": "50957000", "depreciationDepletionAndAmortization": "30464000", "capitalExpenditures": "185118000", "changeInReceivables": "-2359000", "changeInInventory": "97326000", "profitLoss": "-109634000", "cashflowFromInvestment": "654019000", "cashflowFromFinancing": "-8848000", "proceedsFromRepaymentsOfShortTermDebt": "None", "paymentsForRepurchaseOfCommonStock": "None", "paymentsForRepurchaseOfEquity": "None", "paymentsForRepurchaseOfPreferredStock": "None", "dividendPayout": "None", "dividendPayoutCommonStock": "None", "dividendPayoutPreferredStock": "None", "proceedsFromIssuanceOfCommonStock": "None", "proceedsFromIssuanceOfLongTermDebtAndCapitalSecuritiesNet": "4990000", "proceedsFromIssuanceOfPreferredStock": "None", "proceedsFromRepurchaseOfEquity": "3126000", "proceedsFromSaleOfTreasuryStock": "None", "changeInCashAndCashEquivalents": "-109634000", "changeInExchangeRate": "None", "netIncome": "-91354000"}, {"fiscalDateEnding": "2019-09-30", "reportedCurrency": "CAD", "operatingCashflow": "-213795000", "paymentsForOperatingActivities": "None", "proceedsFromOperatingActivities": "None", "changeInOperatingLiabilities": "23166000", "changeInOperatingAssets": "120844000", "depreciationDepletionAndAmortization": "25016000", "capitalExpenditures": "237181000", "changeInReceivables": "2116000", "changeInInventory": "92513000", "profitLoss": "242650000", "cashflowFromInvestment": "-529871000", "cashflowFromFinancing": "19183000", "proceedsFromRepaymentsOfShortTermDebt": "None", "paymentsForRepurchaseOfCommonStock": "None", "paymentsForRepurchaseOfEquity": "None", "paymentsForRepurchaseOfPreferredStock": "None", "dividendPayout": "None", "dividendPayoutCommonStock": "None", "dividendPayoutPreferredStock": "None", "proceedsFromIssuanceOfCommonStock": "None", "proceedsFromIssuanceOfLongTermDebtAndCapitalSecuritiesNet": "None", "proceedsFromIssuanceOfPreferredStock": "None", "proceedsFromRepurchaseOfEquity": "19965000", "proceedsFromSaleOfTreasuryStock": "None", "changeInCashAndCashEquivalents": "242650000", "changeInExchangeRate": "None", "netIncome": "258918000"}, {"fiscalDateEnding": "2019-06-30", "reportedCurrency": "CAD", "operatingCashflow": "-158290000", "paymentsForOperatingActivities": "None", "proceedsFromOperatingActivities": "None", "changeInOperatingLiabilities": "-12582000", "changeInOperatingAssets": "61219000", "depreciationDepletionAndAmortization": "20752000", "capitalExpenditures": "248930000", "changeInReceivables": "-13506000", "changeInInventory": "50716000", "profitLoss": "-194051000", "cashflowFromInvestment": "-405597000", "cashflowFromFinancing": "-81691000", "proceedsFromRepaymentsOfShortTermDebt": "None", "paymentsForRepurchaseOfCommonStock": "None", "paymentsForRepurchaseOfEquity": "None", "paymentsForRepurchaseOfPreferredStock": "None", "dividendPayout": "None", "dividendPayoutCommonStock": "None", "dividendPayoutPreferredStock": "None", "proceedsFromIssuanceOfCommonStock": "None", "proceedsFromIssuanceOfLongTermDebtAndCapitalSecuritiesNet": "None", "proceedsFromIssuanceOfPreferredStock": "None", "proceedsFromRepurchaseOfEquity": "16504000", "proceedsFromSaleOfTreasuryStock": "None", "changeInCashAndCashEquivalents": "-194051000", "changeInExchangeRate": "None", "netIncome": "-185869000"}, {"fiscalDateEnding": "2019-03-31", "reportedCurrency": "CAD", "operatingCashflow": "-347492000", "paymentsForOperatingActivities": "None", "proceedsFromOperatingActivities": "None", "changeInOperatingLiabilities": "None", "changeInOperatingAssets": "None", "depreciationDepletionAndAmortization": "23346000", "capitalExpenditures": "147370000", "changeInReceivables": "None", "changeInInventory": "-67688000", "profitLoss": "-347492000", "cashflowFromInvestment": "-3227985000", "cashflowFromFinancing": "67290000", "proceedsFromRepaymentsOfShortTermDebt": "None", "paymentsForRepurchaseOfCommonStock": "None", "paymentsForRepurchaseOfEquity": "None", "paymentsForRepurchaseOfPreferredStock": "None", "dividendPayout": "None", "dividendPayoutCommonStock": "None", "dividendPayoutPreferredStock": "None", "proceedsFromIssuanceOfCommonStock": "None", "proceedsFromIssuanceOfLongTermDebtAndCapitalSecuritiesNet": "None", "proceedsFromIssuanceOfPreferredStock": "None", "proceedsFromRepurchaseOfEquity": "5294425000", "proceedsFromSaleOfTreasuryStock": "None", "changeInCashAndCashEquivalents": "-347492000", "changeInExchangeRate": "None", "netIncome": "-379516000"}, {"fiscalDateEnding": "2018-12-31", "reportedCurrency": "CAD", "operatingCashflow": "39194000", "paymentsForOperatingActivities": "None", "proceedsFromOperatingActivities": "None", "changeInOperatingLiabilities": "None", "changeInOperatingAssets": "None", "depreciationDepletionAndAmortization": "7890000", "capitalExpenditures": "235857000", "changeInReceivables": "None", "changeInInventory": "-7480485.60", "profitLoss": "39194000", "cashflowFromInvestment": "-219029246.32", "cashflowFromFinancing": "5088877000", "proceedsFromRepaymentsOfShortTermDebt": "None", "paymentsForRepurchaseOfCommonStock": "None", "paymentsForRepurchaseOfEquity": "None", "paymentsForRepurchaseOfPreferredStock": "None", "dividendPayout": "None", "dividendPayoutCommonStock": "None", "dividendPayoutPreferredStock": "None", "proceedsFromIssuanceOfCommonStock": "None", "proceedsFromIssuanceOfLongTermDebtAndCapitalSecuritiesNet": "None", "proceedsFromIssuanceOfPreferredStock": "None", "proceedsFromRepurchaseOfEquity": "809893582.17", "proceedsFromSaleOfTreasuryStock": "None", "changeInCashAndCashEquivalents": "39194000", "changeInExchangeRate": "None", "netIncome": "50736000"}, {"fiscalDateEnding": "2018-09-30", "reportedCurrency": "CAD", "operatingCashflow": "-310428000", "paymentsForOperatingActivities": "None", "proceedsFromOperatingActivities": "None", "changeInOperatingLiabilities": "None", "changeInOperatingAssets": "None", "depreciationDepletionAndAmortization": "9389000", "capitalExpenditures": "143050000", "changeInReceivables": "None", "changeInInventory": "-38890000", "profitLoss": "-310428000", "cashflowFromInvestment": "-193073000", "cashflowFromFinancing": "95073000", "proceedsFromRepaymentsOfShortTermDebt": "None", "paymentsForRepurchaseOfCommonStock": "None", "paymentsForRepurchaseOfEquity": "None", "paymentsForRepurchaseOfPreferredStock": "None", "dividendPayout": "None", "dividendPayoutCommonStock": "None", "dividendPayoutPreferredStock": "None", "proceedsFromIssuanceOfCommonStock": "None", "proceedsFromIssuanceOfLongTermDebtAndCapitalSecuritiesNet": "None", "proceedsFromIssuanceOfPreferredStock": "None", "proceedsFromRepurchaseOfEquity": "None", "proceedsFromSaleOfTreasuryStock": "None", "changeInCashAndCashEquivalents": "-310428000", "changeInExchangeRate": "None", "netIncome": "-317830000"}, {"fiscalDateEnding": "2018-06-30", "reportedCurrency": "CAD", "operatingCashflow": "-93299000", "paymentsForOperatingActivities": "None", "proceedsFromOperatingActivities": "None", "changeInOperatingLiabilities": "None", "changeInOperatingAssets": "None", "depreciationDepletionAndAmortization": "6293000", "capitalExpenditures": "156469000", "changeInReceivables": "None", "changeInInventory": "-16805703.02", "profitLoss": "-93299000", "cashflowFromInvestment": "-138769149.10", "cashflowFromFinancing": "585958000", "proceedsFromRepaymentsOfShortTermDebt": "None", "paymentsForRepurchaseOfCommonStock": "None", "paymentsForRepurchaseOfEquity": "None", "paymentsForRepurchaseOfPreferredStock": "None", "dividendPayout": "None", "dividendPayoutCommonStock": "None", "dividendPayoutPreferredStock": "None", "proceedsFromIssuanceOfCommonStock": "None", "proceedsFromIssuanceOfLongTermDebtAndCapitalSecuritiesNet": "None", "proceedsFromIssuanceOfPreferredStock": "None", "proceedsFromRepurchaseOfEquity": "None", "proceedsFromSaleOfTreasuryStock": "None", "changeInCashAndCashEquivalents": "-93299000", "changeInExchangeRate": "None", "netIncome": "-89671000"}]}